[
    {
        "duree": 188,
        "id": "yRtcYbKoPf0",
        "titre": "K.K. Cruisin' (Animal Crossing) Jazz Cover - The Consouls",
        "playlist": "CHARLY-RADIO (77 titres)",
        "start_minute": 0
    },
    {
        "duree": 207,
        "id": "8F2s8ivKXNY",
        "playlist": "Charly-RapPop",
        "titre": "Oliver Tree - Life Goes On [Music Video]",
        "start_minute": 3.1333333333333333
    },
    {
        "duree": 123,
        "id": "i1N2cclJVys",
        "playlist": "Charly-JPOP",
        "titre": "JoJo's Bizarre Adventure - Opening 8 [4K 60FPS | Creditless | CC]",
        "start_minute": 6.583333333333334
    },
    {
        "duree": 5576,
        "id": "gwt8rbxY8CI",
        "titre": "THE ULTIMATE PERSONA 5 MUSIC COLLECTION (STUDY/WORK)",
        "playlist": "CHARLY-RADIO (77 titres)",
        "start_minute": 8.633333333333333
    },
    {
        "duree": 110,
        "id": "YoeP9w5UIlg",
        "playlist": "Charly-JPOP",
        "titre": "Opening Theme | We Are! | Hiroshi Kitadani",
        "start_minute": 101.56666666666666
    },
    {
        "duree": 109,
        "id": "QUVeKcAT1CI",
        "playlist": "Charly-JPOP",
        "titre": "JoJo's Bizarre Adventure - Opening 5 v2 [4K 60FPS | Creditless | CC]",
        "start_minute": 103.39999999999999
    },
    {
        "duree": 218,
        "id": "FFJRh-ke9YY",
        "playlist": "Charly_Remix",
        "titre": "Alpha Wann - MACRO (Remix)",
        "start_minute": 105.21666666666665
    },
    {
        "duree": 90,
        "id": "dFlDRhvM4L0",
        "playlist": "Charly-JPOP",
        "titre": "『チェンソーマン』ノンクレジットオープニング / CHAINSAW MAN  Opening│米津玄師 「KICK BACK」",
        "start_minute": 108.85
    },
    {
        "duree": 206,
        "id": "LvaEv84Yaws",
        "playlist": "Charly_Remix",
        "titre": "KAARIS - CHARGÉ (BRAZILIAN PHONK REMIX)",
        "start_minute": 110.35
    },
    {
        "duree": 161,
        "id": "gkTQQFGABl8",
        "playlist": "CHARLY-CHILL",
        "titre": "On My Way",
        "start_minute": 113.78333333333333
    },
    {
        "duree": 145,
        "id": "gkmgUjDQJ2c",
        "playlist": "CHARLY-CHILL",
        "titre": "Forget",
        "start_minute": 116.46666666666667
    },
    {
        "duree": 213,
        "id": "wgqUhK32n1c",
        "playlist": "CHARLY-CHILL",
        "titre": "The Door",
        "start_minute": 118.88333333333334
    },
    {
        "duree": 274,
        "id": "cl_AtaYJZpk",
        "playlist": "CHARLY-CHILL",
        "titre": "Moving Forward",
        "start_minute": 122.43333333333334
    },
    {
        "duree": 249,
        "id": "BxqYUbNR-c0",
        "playlist": "CHARLY-CHILL",
        "titre": "サカナクション / 忘れられないの　-Music Video-",
        "start_minute": 127.0
    },
    {
        "duree": 196,
        "id": "wj9OTLIautc",
        "playlist": "CHARLY-CHILL",
        "titre": "Hate Dancin'",
        "start_minute": 131.15
    },
    {
        "duree": 328,
        "id": "WRLwTO_T52U",
        "playlist": "CHARLY-CHILL",
        "titre": "Inner City Blues (Make Me Wanna Holler)",
        "start_minute": 134.41666666666669
    },
    {
        "duree": 266,
        "id": "friqL2l8rNE",
        "playlist": "CHARLY-CHILL",
        "titre": "GOLD",
        "start_minute": 139.88333333333335
    },
    {
        "duree": 231,
        "id": "URR_Nv-6MZs",
        "playlist": "CHARLY-CHILL",
        "titre": "喜劇",
        "start_minute": 144.3166666666667
    },
    {
        "duree": 295,
        "id": "ljEzt2I7IFo",
        "playlist": "CHARLY-CHILL",
        "titre": "King Minos",
        "start_minute": 148.16666666666669
    },
    {
        "duree": 258,
        "id": "lt2cHiJABOI",
        "playlist": "CHARLY-CHILL",
        "titre": "Messy (Sped Up)",
        "start_minute": 153.08333333333334
    },
    {
        "duree": 265,
        "id": "Cu19WlR_UvA",
        "playlist": "CHARLY-CHILL",
        "titre": "Shoody - Tokyo Melody",
        "start_minute": 157.38333333333335
    },
    {
        "duree": 256,
        "id": "5SXX-pWzOY8",
        "playlist": "CHARLY-GROOVE",
        "titre": "Conga",
        "start_minute": 161.8
    },
    {
        "duree": 213,
        "id": "AxyFs_ZbniM",
        "playlist": "Charly-RapPop",
        "titre": "NeS - Le bruit et le silence (Clip officiel)",
        "start_minute": 166.0666666666667
    },
    {
        "duree": 248,
        "id": "5qm8PH4xAss",
        "playlist": "Charly-RapPop",
        "titre": "50 Cent - In Da Club (Official Music Video)",
        "start_minute": 169.6166666666667
    },
    {
        "duree": 314,
        "id": "Je932DsTvmo",
        "playlist": "CHARLY-LOVE",
        "titre": "Sounds of Freedom",
        "start_minute": 173.75000000000003
    },
    {
        "duree": 215,
        "id": "1bDuNZpIFOw",
        "titre": "Men I Trust - Show Me How",
        "playlist": "CHARLY-RADIO (77 titres)",
        "start_minute": 180.0
    },
    {
        "duree": 203,
        "id": "4p2J7y7R0Bk",
        "playlist": "Charly-RapPop",
        "titre": "Lorenzo - Damdamdeo (Clip Officiel)",
        "start_minute": 183.58333333333334
    },
    {
        "duree": 201,
        "id": "E5yFcdPAGv0",
        "titre": "Gorillaz - Humility (Official Video)",
        "playlist": "CHARLY-RADIO (77 titres)",
        "start_minute": 186.96666666666667
    },
    {
        "duree": 202,
        "id": "-e-Uqtuct04",
        "playlist": "Charly-RapPop",
        "titre": "JuL - Toi et moi // 2025",
        "start_minute": 190.31666666666666
    },
    {
        "duree": 290,
        "id": "_CL6n0FJZpk",
        "playlist": "Charly-RapPop",
        "titre": "Dr. Dre - Still D.R.E. ft. Snoop Dogg",
        "start_minute": 193.68333333333334
    },
    {
        "duree": 223,
        "id": "DbN5KsemhA0",
        "playlist": "CHARLY-TROPIQUES",
        "titre": "Stranger",
        "start_minute": 198.51666666666668
    },
    {
        "duree": 170,
        "id": "_Hhz5o9KVHI",
        "playlist": "CHARLY-LOVE",
        "titre": "By Your Side",
        "start_minute": 202.23333333333335
    },
    {
        "duree": 326,
        "id": "0QqSZ5dZH7I",
        "titre": "Oli Howe - Too Many Kicks (Official Audio)",
        "playlist": "CHARLY-RADIO (77 titres)",
        "start_minute": 205.0666666666667
    },
    {
        "duree": 227,
        "id": "rVeMiVU77wo",
        "titre": "alt-J (∆) Breezeblocks",
        "playlist": "CHARLY-RADIO (77 titres)",
        "start_minute": 210.50000000000003
    },
    {
        "duree": 173,
        "id": "Q4yuLqdFWW0",
        "playlist": "Charly-RapPop",
        "titre": "Lorenzo ft. Shy'm - Nous Deux (Clip Officiel)",
        "start_minute": 214.28333333333336
    },
    {
        "duree": 133,
        "id": "XjNlP3LrFiY",
        "playlist": "Charly-RapPop",
        "titre": "bbno$ - gigolo (starring Ethan Nestor)",
        "start_minute": 217.16666666666669
    },
    {
        "duree": 124,
        "id": "SJkCLcnGB-c",
        "playlist": "Charly-JPOP",
        "titre": "JoJo's Bizarre Adventure - Opening 2 [4K 60FPS | Creditless | CC]",
        "start_minute": 219.38333333333335
    },
    {
        "duree": 307,
        "id": "MR3uP7IYz44",
        "playlist": "CHARLY-GROOVE",
        "titre": "Lady (Hear Me Tonight)",
        "start_minute": 221.45000000000002
    },
    {
        "duree": 273,
        "id": "pz-wVSPU-8Q",
        "playlist": "Charly-RapPop",
        "titre": "Booba - Ecoute bien",
        "start_minute": 226.5666666666667
    },
    {
        "duree": 147,
        "id": "zNWO0dXoQhc",
        "titre": "Lost & Dizzy",
        "playlist": "CHARLY-RADIO (77 titres)",
        "start_minute": 231.1166666666667
    },
    {
        "duree": 100,
        "id": "VtNgeDxYJzE",
        "playlist": "Charly-JPOP",
        "titre": "『僕のヒーローアカデミア』第4期ノンクレジットオープニング映像／OPテーマ：「ポラリス」BLUE ENCOUNT／ヒロアカOP",
        "start_minute": 233.5666666666667
    },
    {
        "duree": 100,
        "id": "qPdPjWkJZF8",
        "playlist": "Charly-JPOP",
        "titre": "DAN DA DAN - Opening | Otonoke de Creepy Nuts",
        "start_minute": 235.23333333333335
    },
    {
        "duree": 315,
        "id": "LzcWTjY3b8Q",
        "titre": "King Gizzard & The Lizard Wizard - Interior People (Official Video)",
        "playlist": "CHARLY-RADIO (77 titres)",
        "start_minute": 236.9
    },
    {
        "duree": 189,
        "id": "tYdwajzKMck",
        "playlist": "Charly-RapPop",
        "titre": "Casseurs Flowters Infinity",
        "start_minute": 242.15
    },
    {
        "duree": 245,
        "id": "VYOjWnS4cMY",
        "playlist": "Charly-RapPop",
        "titre": "Childish Gambino - This Is America (Official Video)",
        "start_minute": 245.3
    },
    {
        "duree": 216,
        "id": "rDVOqLGZgW0",
        "playlist": "CHARLY-LOVE",
        "titre": "Day & Night (feat. Holybrune)",
        "start_minute": 249.38333333333335
    },
    {
        "duree": 221,
        "id": "Z28jtA4Cjvw",
        "playlist": "CHARLY-GROOVE",
        "titre": "Assumptions",
        "start_minute": 252.98333333333335
    },
    {
        "duree": 100,
        "id": "umqzznKblJ0",
        "playlist": "Charly-JPOP",
        "titre": "Mob Psycho 100 III - Opening | 1",
        "start_minute": 256.6666666666667
    },
    {
        "duree": 227,
        "id": "Kbj2Zss-5GY",
        "playlist": "Charly-RapPop",
        "titre": "A$AP Rocky - Praise The Lord (Da Shine) (Official Video) ft. Skepta",
        "start_minute": 258.33333333333337
    },
    {
        "duree": 153,
        "id": "gZxmkRFOQws",
        "playlist": "CHARLY-LOVE",
        "titre": "Tell Me Where To Go (feat. Apollo J, Zay Suav, Marcus Isiah & Rshad)",
        "start_minute": 262.11666666666673
    },
    {
        "duree": 137,
        "id": "LiXYi-_MVa4",
        "playlist": "Charly-RapPop",
        "titre": "bbno$ - two (official music video)",
        "start_minute": 264.66666666666674
    },
    {
        "duree": 183,
        "id": "wd9_QCH8Eq4",
        "playlist": "CHARLY-GROOVE",
        "titre": "Don't Start Now",
        "start_minute": 266.9500000000001
    },
    {
        "duree": 191,
        "id": "NoqKkw4azn8",
        "titre": "Calipso",
        "playlist": "CHARLY-RADIO (77 titres)",
        "start_minute": 270.0000000000001
    },
    {
        "duree": 350,
        "id": "rxdGfg0Nwzs",
        "playlist": "CHARLY-RUSH",
        "titre": "Ego Death (feat. Steve Vai)",
        "start_minute": 273.18333333333345
    },
    {
        "duree": 245,
        "id": "xPpr__dmFHc",
        "playlist": "Charly-RapPop",
        "titre": "OrelSan - Plus rien ne m'Étonne [CLIP OFFICIEL]",
        "start_minute": 279.01666666666677
    },
    {
        "duree": 374,
        "id": "-CVn3-3g_BI",
        "playlist": "Charly-RapPop",
        "titre": "Bande Organisée - SCH / Kofs / Jul / Naps / Soso Maness / Elams / Solda / Houari // Clip Officiel",
        "start_minute": 283.1000000000001
    },
    {
        "duree": 209,
        "id": "LnOts74hPhU",
        "playlist": "CHARLY-RUSH",
        "titre": "Dance!",
        "start_minute": 289.3333333333334
    },
    {
        "duree": 169,
        "id": "d2tnwgcBfoA",
        "playlist": "Charly-RapPop",
        "titre": "THEODORA - KONGOLESE SOUS BBL (FT. JEEZ SUAVE)",
        "start_minute": 292.8166666666668
    },
    {
        "duree": 213,
        "id": "xXWqZx0wuiM",
        "playlist": "CHARLY-TROPIQUES",
        "titre": "El Niño (Mixed by Chris Goss)",
        "start_minute": 295.63333333333344
    },
    {
        "duree": 191,
        "id": "xSHGzO4FzBA",
        "playlist": "Charly-RapPop",
        "titre": "Gambi - HÉ OH (Clip officiel)",
        "start_minute": 299.18333333333345
    },
    {
        "duree": 158,
        "id": "u5heWZ9occg",
        "playlist": "Charly-JPOP",
        "titre": "Wild Side",
        "start_minute": 302.3666666666668
    },
    {
        "duree": 177,
        "id": "7qmRSBHZp5s",
        "playlist": "Charly_Remix",
        "titre": "1PLIKE140 - CANADA - HOUSE REMIX (Kungs - This Girl)",
        "start_minute": 305.0000000000001
    },
    {
        "duree": 294,
        "id": "1AVxBedMP4I",
        "playlist": "CHARLY-GROOVE",
        "titre": "Get Down On It",
        "start_minute": 307.9500000000001
    },
    {
        "duree": 336,
        "id": "Yk9mnW45Eqk",
        "titre": "We're on the Move",
        "playlist": "CHARLY-RADIO (77 titres)",
        "start_minute": 312.8500000000001
    },
    {
        "duree": 116,
        "id": "T4dUEFxRBL0",
        "playlist": "Charly-JPOP",
        "titre": "JoJo's Bizarre Adventure - Opening 7 v1 [4K 60FPS | Creditless | CC]",
        "start_minute": 318.4500000000001
    },
    {
        "duree": 228,
        "id": "OWiVJMgms9E",
        "playlist": "CHARLY-GROOVE",
        "titre": "Voyager",
        "start_minute": 320.38333333333344
    },
    {
        "duree": 412,
        "id": "e6vOwy_1kwQ",
        "playlist": "CHARLY-TROPIQUES",
        "titre": "Kryé Mwen (Patchworks Remix)",
        "start_minute": 324.18333333333345
    },
    {
        "duree": 188,
        "id": "yRtcYbKoPf0",
        "titre": "K.K. Cruisin' (Animal Crossing) Jazz Cover - The Consouls",
        "playlist": "CHARLY-RADIO (77 titres)",
        "start_minute": 331.0500000000001
    },
    {
        "duree": 222,
        "id": "CmZDCflUYWk",
        "playlist": "Charly_Remix",
        "titre": "Alpha Wann x Romsii - Carrelage Italien  (Remix)",
        "start_minute": 334.18333333333345
    },
    {
        "duree": 249,
        "id": "9RHFFeQ2tu4",
        "titre": "Fever The Ghost - SOURCE (official music video)",
        "playlist": "CHARLY-RADIO (77 titres)",
        "start_minute": 337.88333333333344
    },
    {
        "duree": 209,
        "id": "n0GXk_T2zs8",
        "playlist": "CHARLY-GROOVE",
        "titre": "Training Season",
        "start_minute": 342.0333333333334
    },
    {
        "duree": 545,
        "id": "Njk2YAgNMnE",
        "titre": "King Gizzard & The Lizard Wizard - Iron Lung",
        "playlist": "CHARLY-RADIO (77 titres)",
        "start_minute": 345.51666666666677
    },
    {
        "duree": 280,
        "id": "ony539T074w",
        "playlist": "Charly-JPOP",
        "titre": "King Gnu - 白日",
        "start_minute": 354.6000000000001
    },
    {
        "duree": 236,
        "id": "_B943OFlHVs",
        "playlist": "CHARLY-RUSH",
        "titre": "Right Here, Right Now",
        "start_minute": 359.26666666666677
    },
    {
        "duree": 207,
        "id": "ON0GouHEgRE",
        "playlist": "Charly_Remix",
        "titre": "Josman x Alpha Wann - Le château ambulant (Prod. HERB)",
        "start_minute": 363.2000000000001
    },
    {
        "duree": 203,
        "id": "AVz2FAp9odU",
        "playlist": "CHARLY-GROOVE",
        "titre": "Skate",
        "start_minute": 366.6500000000001
    },
    {
        "duree": 181,
        "id": "iZ0cGpcQ1oI",
        "playlist": "Charly_Remix",
        "titre": "Kaaris x Super Mario World - INTRO (Phonk Remix)",
        "start_minute": 370.0333333333334
    },
    {
        "duree": 238,
        "id": "HbXaUmWaU5Q",
        "titre": "忘れられないの",
        "playlist": "CHARLY-RADIO (77 titres)",
        "start_minute": 373.05000000000007
    },
    {
        "duree": 78,
        "id": "YIU3SaX7GiQ",
        "playlist": "CHARLY-LOVE",
        "titre": "\"Special\"- Smile High featuring Antwaun Stanley",
        "start_minute": 377.0166666666667
    },
    {
        "duree": 249,
        "id": "nlZDv8yuxCc",
        "playlist": "CHARLY-LOVE",
        "titre": "After Last Night (with Thundercat & Bootsy Collins)",
        "start_minute": 378.3166666666667
    },
    {
        "duree": 238,
        "id": "mEhYtnHQAUw",
        "playlist": "CHARLY-GROOVE",
        "titre": "Say So",
        "start_minute": 382.4666666666667
    },
    {
        "duree": 204,
        "id": "vTMSj7gDEGs",
        "playlist": "CHARLY-GROOVE",
        "titre": "Sing a Song",
        "start_minute": 386.43333333333334
    },
    {
        "duree": 218,
        "id": "1t_sMynan_k",
        "playlist": "Charly-RapPop",
        "titre": "LITTLE BIG – FARADENZA (official music video)",
        "start_minute": 389.8333333333333
    },
    {
        "duree": 147,
        "id": "eenLOHk8dtc",
        "playlist": "Charly_Remix",
        "titre": "ZIAK GALERIE DISCO [ remix ]",
        "start_minute": 393.46666666666664
    },
    {
        "duree": 206,
        "id": "xC8fNydumzs",
        "playlist": "Charly-RapPop",
        "titre": "JuL - J'ai tout su // clip officiel // 2022",
        "start_minute": 395.91666666666663
    },
    {
        "duree": 188,
        "id": "361GUUBHH5Y",
        "playlist": "Charly_Remix",
        "titre": "Alpha Wann x Nujabes - ÇA VA ENSEMBLE II (remix)",
        "start_minute": 399.34999999999997
    },
    {
        "duree": 187,
        "id": "0bkBRHRYtcQ",
        "playlist": "Charly-RapPop",
        "titre": "OrelSan - Soleil Levant (feat. SDM) [CLIP OFFICIEL]",
        "start_minute": 402.4833333333333
    },
    {
        "duree": 200,
        "id": "3xSb5Pm-ws8",
        "playlist": "CHARLY-TROPIQUES",
        "titre": "Lihue",
        "start_minute": 405.59999999999997
    },
    {
        "duree": 137,
        "id": "EiV1YxtbfcE",
        "playlist": "Charly_Remix",
        "titre": "Angèle - Saiyan [IA] (prod. Lnkhey)",
        "start_minute": 408.9333333333333
    },
    {
        "duree": 123,
        "id": "L9DK-DRg85w",
        "playlist": "Charly-JPOP",
        "titre": "JoJo's Bizarre Adventure - Opening 3 [4K 60FPS | Creditless | CC]",
        "start_minute": 411.21666666666664
    },
    {
        "duree": 306,
        "id": "h4UqMyldS7Q",
        "playlist": "Charly-RapPop",
        "titre": "Ice Cube - It Was A Good Day",
        "start_minute": 413.26666666666665
    },
    {
        "duree": 436,
        "id": "0RXdd0pCJ9Q",
        "titre": "DWIG - Orange Evening // Laut & Luise (LUL007)",
        "playlist": "CHARLY-RADIO (77 titres)",
        "start_minute": 420.0
    },
    {
        "duree": 150,
        "id": "Wgw6tJ8yz9M",
        "titre": "JAWNY - Honeypie (Official Video)",
        "playlist": "CHARLY-RADIO (77 titres)",
        "start_minute": 427.26666666666665
    },
    {
        "duree": 207,
        "id": "K1ROjN6cyeo",
        "titre": "Light You Up (feat. PV Nova, Tices)",
        "playlist": "CHARLY-RADIO (77 titres)",
        "start_minute": 429.76666666666665
    },
    {
        "duree": 207,
        "id": "5lRos06sBm4",
        "titre": "United (feat. Antwaun Stanley)",
        "playlist": "CHARLY-RADIO (77 titres)",
        "start_minute": 433.21666666666664
    },
    {
        "duree": 340,
        "id": "alZZeDr4wxY",
        "titre": "Work It Out (feat. Antwaun Stanley)",
        "playlist": "CHARLY-RADIO (77 titres)",
        "start_minute": 436.66666666666663
    },
    {
        "duree": 203,
        "id": "bsG6UFfemhU",
        "titre": "Out Of Love",
        "playlist": "CHARLY-RADIO (77 titres)",
        "start_minute": 442.3333333333333
    },
    {
        "duree": 217,
        "id": "GgvMSSiZMi8",
        "titre": "Cosmic Sans (feat. Tom Misch)",
        "playlist": "CHARLY-RADIO (77 titres)",
        "start_minute": 445.71666666666664
    },
    {
        "duree": 82,
        "id": "q4i05EaML44",
        "titre": "Bloopin",
        "playlist": "CHARLY-RADIO (77 titres)",
        "start_minute": 449.3333333333333
    },
    {
        "duree": 248,
        "id": "VbD_kBJc_gI",
        "titre": "David Bowie - Let's Dance (Official Video) [HD]",
        "playlist": "CHARLY-RADIO (77 titres)",
        "start_minute": 450.7
    },
    {
        "duree": 265,
        "id": "FxzBvqY5PP0",
        "titre": "Daft Punk - Digital Love (Official Video)",
        "playlist": "CHARLY-RADIO (77 titres)",
        "start_minute": 454.8333333333333
    },
    {
        "duree": 194,
        "id": "BiVgcPhokbY",
        "titre": "Conor Albert & ELSAS - Stuck In The Middle",
        "playlist": "CHARLY-RADIO (77 titres)",
        "start_minute": 459.25
    },
    {
        "duree": 102,
        "id": "mhRj1b8hVMc",
        "titre": "Dead Inside Shuffle - Louis Cole",
        "playlist": "CHARLY-RADIO (77 titres)",
        "start_minute": 462.48333333333335
    },
    {
        "duree": 126,
        "id": "oHee6cG6Ubk",
        "titre": "Adieu les filles",
        "playlist": "CHARLY-RADIO (77 titres)",
        "start_minute": 464.18333333333334
    },
    {
        "duree": 215,
        "id": "XX4ciZy6Or0",
        "titre": "Macaulkin & The Robots - Ces Soirées-Là (2024) [ft RobotSan, RobotAngele + Guests]",
        "playlist": "CHARLY-RADIO (77 titres)",
        "start_minute": 466.28333333333336
    },
    {
        "duree": 188,
        "id": "5xyoPwocD08",
        "titre": "Julien Granel - PLUS FORT",
        "playlist": "CHARLY-RADIO (77 titres)",
        "start_minute": 469.8666666666667
    },
    {
        "duree": 263,
        "id": "-pnBR0Ec7yc",
        "titre": "catching a vibe with my 1973 Fender Rhodes Mark I",
        "playlist": "CHARLY-RADIO (77 titres)",
        "start_minute": 473.0
    },
    {
        "duree": 326,
        "id": "eK5ozrSgqeI",
        "titre": "Passing Breeze from \"Outrun\" - Big Band Jazz version (The 8-Bit Big Band)",
        "playlist": "CHARLY-RADIO (77 titres)",
        "start_minute": 477.3833333333333
    },
    {
        "duree": 262,
        "id": "RyE7R5fgR60",
        "titre": "Tom Misch - 'It Runs Through Me' (Feat. De La Soul)",
        "playlist": "CHARLY-RADIO (77 titres)",
        "start_minute": 482.81666666666666
    },
    {
        "duree": 197,
        "id": "Fz7D8u9mYGA",
        "titre": "Breakbot - Get Lost (Official Video)",
        "playlist": "CHARLY-RADIO (77 titres)",
        "start_minute": 487.18333333333334
    },
    {
        "duree": 100,
        "id": "6riDJMI-Y8U",
        "titre": "JUJUTSU KAISEN Ending | Lost in Paradise feat. AKLO",
        "playlist": "CHARLY-RADIO (77 titres)",
        "start_minute": 490.4666666666667
    },
    {
        "duree": 293,
        "id": "jhOVibLEDhA",
        "titre": "星野源 – 恋 (Official Video)",
        "playlist": "CHARLY-RADIO (77 titres)",
        "start_minute": 492.1333333333334
    },
    {
        "duree": 340,
        "id": "09Ig2MeSmSQ",
        "titre": "Tempos Futuros (feat. Jose Roberto Bertrami)",
        "playlist": "CHARLY-RADIO (77 titres)",
        "start_minute": 497.0166666666667
    },
    {
        "duree": 172,
        "id": "hpjV962DLWs",
        "titre": "Vladimir Cauchemar - Aulos (Official Music Video)",
        "playlist": "CHARLY-RADIO (77 titres)",
        "start_minute": 502.6833333333334
    },
    {
        "duree": 289,
        "id": "_ScM9pKlCfo",
        "titre": "Daft Punk - Fragments of Time (Official Audio) ft. Todd Edwards",
        "playlist": "CHARLY-RADIO (77 titres)",
        "start_minute": 505.55000000000007
    },
    {
        "duree": 178,
        "id": "LzHGYtIqLig",
        "titre": "Dirty Projectors - Overlord (Official Music Video)",
        "playlist": "CHARLY-RADIO (77 titres)",
        "start_minute": 510.36666666666673
    },
    {
        "duree": 155,
        "id": "6okxuiiHx2w",
        "titre": "Breakbot - Baby I'm Yours (feat. Irfane) [Official Video]",
        "playlist": "CHARLY-RADIO (77 titres)",
        "start_minute": 513.3333333333334
    },
    {
        "duree": 150,
        "id": "DH_mL6zwCCw",
        "titre": "Anatole Muster & daniel hayn - Passerby (feat. Tane)",
        "playlist": "CHARLY-RADIO (77 titres)",
        "start_minute": 515.9166666666667
    },
    {
        "duree": 198,
        "id": "JRF8Nko1EDY",
        "titre": "King Gizzard & The Lizard Wizard - Hate Dancin'",
        "playlist": "CHARLY-RADIO (77 titres)",
        "start_minute": 518.4166666666667
    },
    {
        "duree": 174,
        "id": "LbYwT6TULjg",
        "titre": "Freaking Out the Neighborhood",
        "playlist": "CHARLY-RADIO (77 titres)",
        "start_minute": 521.7166666666667
    },
    {
        "duree": 193,
        "id": "zgdufCDrulI",
        "titre": "MydNyte",
        "playlist": "CHARLY-RADIO (77 titres)",
        "start_minute": 524.6166666666667
    },
    {
        "duree": 213,
        "id": "dQw4w9WgXcQ",
        "titre": "Rick Astley - Never Gonna Give You Up (Official Video) (4K Remaster)",
        "playlist": "CHARLY-RADIO (77 titres)",
        "start_minute": 527.8333333333334
    },
    {
        "duree": 185,
        "id": "hrZduVyfoEs",
        "titre": "Heavy, California",
        "playlist": "CHARLY-RADIO (77 titres)",
        "start_minute": 531.3833333333333
    },
    {
        "duree": 256,
        "id": "KOOhPfMbuIQ",
        "titre": "half•alive - still feel. [OFFICIAL VIDEO]",
        "playlist": "CHARLY-RADIO (77 titres)",
        "start_minute": 534.4666666666667
    },
    {
        "duree": 278,
        "id": "ZwAAqeOYLJE",
        "titre": "Up Top",
        "playlist": "CHARLY-RADIO (77 titres)",
        "start_minute": 538.7333333333333
    },
    {
        "duree": 281,
        "id": "EXWOJvlDwbU",
        "titre": "Tom Misch - Disco Yes (feat. Poppy Ajudha) [Official Audio]",
        "playlist": "CHARLY-RADIO (77 titres)",
        "start_minute": 543.3666666666667
    },
    {
        "duree": 200,
        "id": "Nq5LMGtBmis",
        "titre": "VULFPECK /// It Gets Funkier IV (feat. Louis Cole)",
        "playlist": "CHARLY-RADIO (77 titres)",
        "start_minute": 548.05
    },
    {
        "duree": 218,
        "id": "qfgfY_gB1Eg",
        "titre": "Space Cowboy (Remastered 2006)",
        "playlist": "CHARLY-RADIO (77 titres)",
        "start_minute": 551.3833333333333
    },
    {
        "duree": 203,
        "id": "CEw-7cMnBDY",
        "titre": "Bruno Mars, Anderson .Paak, Silk Sonic - Skate [Official Music Video]",
        "playlist": "CHARLY-RADIO (77 titres)",
        "start_minute": 555.0166666666667
    },
    {
        "duree": 235,
        "id": "4JkIs37a2JE",
        "titre": "Jamiroquai - Virtual Insanity (Official Video)",
        "playlist": "CHARLY-RADIO (77 titres)",
        "start_minute": 558.4
    },
    {
        "duree": 632,
        "id": "56Ju68VyKVk",
        "titre": "BEAT FUNKTION - THE PLUNGE : Official Music Video",
        "playlist": "CHARLY-RADIO (77 titres)",
        "start_minute": 562.3166666666666
    },
    {
        "duree": 258,
        "id": "swJOIjjW69U",
        "titre": "Dreams (2004 Remaster)",
        "playlist": "CHARLY-RADIO (77 titres)",
        "start_minute": 572.8499999999999
    },
    {
        "duree": 196,
        "id": "2Od7QCsyqkE",
        "titre": "【MV】鈴木雅之『DADDY ! DADDY ! DO ! feat. 鈴木愛理』TVアニメ「かぐや様は告らせたい？～天才たちの恋愛頭脳戦～」OP主題歌",
        "playlist": "CHARLY-RADIO (77 titres)",
        "start_minute": 577.1499999999999
    },
    {
        "duree": 212,
        "id": "hXzPxBhhmY8",
        "titre": "I DONT KNOW HOW BUT THEY FOUND ME - Do It All The Time",
        "playlist": "CHARLY-RADIO (77 titres)",
        "start_minute": 580.4166666666665
    },
    {
        "duree": 141,
        "id": "M3-9HlYPZRk",
        "titre": "Wow Wow Wow",
        "playlist": "CHARLY-RADIO (77 titres)",
        "start_minute": 583.9499999999998
    },
    {
        "duree": 90,
        "id": "210R0ozmLwg",
        "titre": "TVアニメ「マッシュル-MASHLE-」第2期ノンクレジットOPムービー｜Creepy Nuts「Bling-Bang-Bang-Born」#BBBBダンス",
        "playlist": "CHARLY-RADIO (77 titres)",
        "start_minute": 586.2999999999998
    },
    {
        "duree": 193,
        "id": "NMA_isZYsYQ",
        "titre": "KICK BACK",
        "playlist": "CHARLY-RADIO (77 titres)",
        "start_minute": 587.7999999999998
    },
    {
        "duree": 100,
        "id": "GwaRztMaoY0",
        "titre": "JUJUTSU KAISEN Opening | Kaikai Kitan by Eve",
        "playlist": "CHARLY-RADIO (77 titres)",
        "start_minute": 591.0166666666665
    },
    {
        "duree": 436,
        "id": "0RXdd0pCJ9Q",
        "titre": "DWIG - Orange Evening // Laut & Luise (LUL007)",
        "playlist": "CHARLY-RADIO (77 titres)",
        "start_minute": 592.6833333333332
    },
    {
        "duree": 201,
        "id": "E5yFcdPAGv0",
        "titre": "Gorillaz - Humility (Official Video)",
        "playlist": "CHARLY-RADIO (77 titres)",
        "start_minute": 600.0
    },
    {
        "duree": 280,
        "id": "CnJsQQWrmiM",
        "playlist": "CHARLY-RUSH",
        "titre": "Sneaky Driver",
        "start_minute": 603.35
    },
    {
        "duree": 229,
        "id": "IYSWouOTqwk",
        "playlist": "CHARLY-RUSH",
        "titre": "Dynamite",
        "start_minute": 608.0166666666667
    },
    {
        "duree": 394,
        "id": "aE-qRua89Ak",
        "playlist": "CHARLY-RUSH",
        "titre": "I Remember",
        "start_minute": 611.8333333333334
    },
    {
        "duree": 109,
        "id": "gTw22MVAk1E",
        "playlist": "CHARLY-RUSH",
        "titre": "Chaos at the Spaceship",
        "start_minute": 618.4000000000001
    },
    {
        "duree": 220,
        "id": "Ojj8mR8PEbw",
        "playlist": "CHARLY-RUSH",
        "titre": "Travelling Without Moving (Remastered 2013)",
        "start_minute": 620.2166666666668
    },
    {
        "duree": 203,
        "id": "rIcwQ-Jy9sE",
        "playlist": "CHARLY-RUSH",
        "titre": "Operaz (feat. Youthstar, ASM)",
        "start_minute": 623.8833333333334
    },
    {
        "duree": 271,
        "id": "OuIRPaeXNqo",
        "playlist": "CHARLY-RUSH",
        "titre": "Megaphone",
        "start_minute": 627.2666666666668
    },
    {
        "duree": 213,
        "id": "m9SMT5ipbxk",
        "playlist": "CHARLY-RUSH",
        "titre": "アイドル",
        "start_minute": 631.7833333333334
    },
    {
        "duree": 253,
        "id": "qkaf5sASfc8",
        "playlist": "CHARLY-RUSH",
        "titre": "春に揺られど君想う (feat. こぴ)",
        "start_minute": 635.3333333333334
    },
    {
        "duree": 123,
        "id": "jioq9wc57fE",
        "playlist": "CHARLY-RUSH",
        "titre": "Violet",
        "start_minute": 639.5500000000001
    },
    {
        "duree": 296,
        "id": "pRo4oXEgk4g",
        "playlist": "CHARLY-RUSH",
        "titre": "我愛你",
        "start_minute": 641.6
    },
    {
        "duree": 196,
        "id": "-kCqSaspG7Q",
        "playlist": "CHARLY-RUSH",
        "titre": "Failing in a Cool Way",
        "start_minute": 646.5333333333333
    },
    {
        "duree": 286,
        "id": "0dOkB7Mhtt0",
        "playlist": "CHARLY-GROOVE",
        "titre": "Sticky Like Glue",
        "start_minute": 649.8
    },
    {
        "duree": 190,
        "id": "4qWc_6u4V9M",
        "playlist": "Charly-JPOP",
        "titre": "ATARASHII GAKKO! - NAINAINAI (Official Video)",
        "start_minute": 654.5666666666666
    },
    {
        "duree": 125,
        "id": "Ir-IkSLGPBQ",
        "playlist": "Charly-JPOP",
        "titre": "JoJo's Bizarre Adventure - Opening 11 v1 【Heaven’s falling down】 4K 60FPS Creditless | CC",
        "start_minute": 657.7333333333332
    },
    {
        "duree": 452,
        "id": "NqThf-MpCjs",
        "playlist": "CHARLY-GROOVE",
        "titre": "Gypsy Woman (She's Homeless) (La Da Dee La Da Da) (Basement Boy Strip To The Bone Mix)",
        "start_minute": 659.8166666666666
    },
    {
        "duree": 113,
        "id": "JGVUBSZ0SC4",
        "playlist": "Charly-JPOP",
        "titre": "JoJo ★ The JOJOLands OP 1 ★『Make It Rain』Original JoJo's Bizarre Adventure Part 9【ジョジョの奇妙な冒険】ジョジョランズ",
        "start_minute": 667.3499999999999
    },
    {
        "duree": 124,
        "id": "Z49Ig-ssupM",
        "playlist": "Charly_Remix",
        "titre": "Donde Estas Yolanda X The Largest [CEEZY REMIX]",
        "start_minute": 669.2333333333332
    },
    {
        "duree": 127,
        "id": "zG-sG8kGvbE",
        "playlist": "Charly-RapPop",
        "titre": "VALD - DANS LA RUE (le clip officiel)",
        "start_minute": 671.3
    },
    {
        "duree": 328,
        "id": "xFYQQPAOz7Y",
        "playlist": "Charly-RapPop",
        "titre": "Eminem - Lose Yourself",
        "start_minute": 673.4166666666666
    },
    {
        "duree": 268,
        "id": "eJO5HU_7_1w",
        "playlist": "Charly-RapPop",
        "titre": "Eminem - The Real Slim Shady (Official Video - Clean Version)",
        "start_minute": 678.8833333333333
    },
    {
        "duree": 242,
        "id": "IYFqc9gk4qI",
        "playlist": "CHARLY-LOVE",
        "titre": "Leave The Door Open",
        "start_minute": 683.35
    },
    {
        "duree": 262,
        "id": "krJ7k1gG_28",
        "playlist": "Charly-RapPop",
        "titre": "Bigflo & Oli - INSOLENT #5",
        "start_minute": 687.3833333333333
    },
    {
        "duree": 180,
        "id": "GfLDnW4i31g",
        "playlist": "Charly-RapPop",
        "titre": "particule",
        "start_minute": 691.75
    },
    {
        "duree": 226,
        "id": "r7-A9NqUjRI",
        "playlist": "CHARLY-GROOVE",
        "titre": "24K Magic",
        "start_minute": 694.75
    },
    {
        "duree": 97,
        "id": "6BrHcmH3Gyk",
        "playlist": "Charly-JPOP",
        "titre": "『僕のヒーローアカデミア』6期第1クールノンクレジットオープニング映像／OPテーマ：「ひたむき」SUPER BEAVER／ヒロアカOP",
        "start_minute": 698.5166666666667
    },
    {
        "duree": 571,
        "id": "MU1lAkDJwU4",
        "playlist": "CHARLY-TROPIQUES",
        "titre": "You No Fit Touch Am (Medlar Remix)",
        "start_minute": 700.1333333333333
    },
    {
        "duree": 197,
        "id": "HwyvWnWX03c",
        "playlist": "CHARLY-GROOVE",
        "titre": "Dj Kayz Soirée Ft Mokobé,Dry,Dieselle",
        "start_minute": 709.65
    },
    {
        "duree": 100,
        "id": "2upuBiEiXDk",
        "playlist": "Charly-JPOP",
        "titre": "Naruto Shippuden Opening 3 | Blue Bird",
        "start_minute": 712.9333333333333
    },
    {
        "duree": 186,
        "id": "944iJyGtpF4",
        "playlist": "Charly_Remix",
        "titre": "Ninho ft Leto, Ziak, The Supermen Lovers",
        "start_minute": 714.5999999999999
    },
    {
        "duree": 215,
        "id": "1bDuNZpIFOw",
        "titre": "Men I Trust - Show Me How",
        "playlist": "CHARLY-RADIO (77 titres)",
        "start_minute": 717.6999999999999
    },
    {
        "duree": 240,
        "id": "llPHj_3-BQU",
        "playlist": "CHARLY-GROOVE",
        "titre": "Van La Ka Vante (Omar Mendez TD Fix)",
        "start_minute": 721.2833333333333
    },
    {
        "duree": 252,
        "id": "m5MM_QSiYM8",
        "playlist": "CHARLY-HOUSE",
        "titre": "Ariane",
        "start_minute": 725.2833333333333
    },
    {
        "duree": 170,
        "id": "I6UA589JoKs",
        "playlist": "CHARLY-TROPIQUES",
        "titre": "The Traveller",
        "start_minute": 729.4833333333333
    },
    {
        "duree": 96,
        "id": "b3f6Shks9g4",
        "playlist": "Charly-JPOP",
        "titre": "『僕のヒーローアカデミア』ヒロアカ7期第2クールOPノンクレジット映像／OPテーマ：「カーテンコール」優里",
        "start_minute": 732.3166666666667
    },
    {
        "duree": 215,
        "id": "KWoTyfPsqbE",
        "playlist": "Charly-RapPop",
        "titre": "Sabrina Carpenter - House Tour (Official Video)",
        "start_minute": 733.9166666666667
    },
    {
        "duree": 208,
        "id": "6Ro7NubzE9A",
        "playlist": "Charly-RapPop",
        "titre": "bbno$ - 1-800 (ft. ironmouse)",
        "start_minute": 737.5000000000001
    },
    {
        "duree": 233,
        "id": "QK8mJJJvaes",
        "playlist": "Charly-RapPop",
        "titre": "MACKLEMORE & RYAN LEWIS - THRIFT SHOP FEAT. WANZ (OFFICIAL VIDEO)",
        "start_minute": 740.9666666666668
    },
    {
        "duree": 105,
        "id": "9O-nn93Z5p4",
        "playlist": "Charly-RapPop",
        "titre": "HEM - Zinzin (Clip officiel)",
        "start_minute": 744.8500000000001
    },
    {
        "duree": 301,
        "id": "Omnpu8mzX4c",
        "playlist": "CHARLY-GROOVE",
        "titre": "Give Me the Night",
        "start_minute": 746.6000000000001
    },
    {
        "duree": 305,
        "id": "UgS7vgquBvo",
        "playlist": "Charly-JPOP",
        "titre": "KANA-BOON 『ないものねだり』Music Video",
        "start_minute": 751.6166666666668
    },
    {
        "duree": 286,
        "id": "ddZb5LIggzs",
        "playlist": "CHARLY-GROOVE",
        "titre": "The Grid Generation (feat. Louis Cole)",
        "start_minute": 756.7000000000002
    },
    {
        "duree": 97,
        "id": "BGBQkvPAzSY",
        "playlist": "Charly-JPOP",
        "titre": "『僕のヒーローアカデミア』1期ノンクレジットオープニング映像／OPテーマ：「THE DAY」ポルノグラフィティ／ヒロアカOP",
        "start_minute": 761.4666666666668
    },
    {
        "duree": 264,
        "id": "BC4zaaiXNMI",
        "playlist": "CHARLY-GROOVE",
        "titre": "Love Dramatic",
        "start_minute": 763.0833333333335
    },
    {
        "duree": 96,
        "id": "AwXRPWmgLbU",
        "playlist": "Charly-JPOP",
        "titre": "TVアニメ『よふかしのうた』ノンクレジットOP 【Creepy Nuts「堕天」】| 毎週木曜日24時55分からフジテレビ\"ノイタミナ\"ほかにて放送中！",
        "start_minute": 767.4833333333335
    },
    {
        "duree": 185,
        "id": "qWpBduQKTMY",
        "playlist": "Charly-RapPop",
        "titre": "Jul - On M'appelle L'ovni // Clip Officiel // 2016",
        "start_minute": 769.0833333333335
    },
    {
        "duree": 193,
        "id": "mDFBTdToRmw",
        "playlist": "Charly-RapPop",
        "titre": "LITTLE BIG – SKIBIDI (official music video)",
        "start_minute": 772.1666666666669
    },
    {
        "duree": 126,
        "id": "iSyX-aGYHYk",
        "playlist": "Charly-RapPop",
        "titre": "bbno$ - check (official music video)",
        "start_minute": 775.3833333333336
    },
    {
        "duree": 228,
        "id": "dqNEmR5uQCM",
        "playlist": "Charly-RapPop",
        "titre": "Booba - GLAIVE (Clip Officiel)",
        "start_minute": 777.4833333333336
    },
    {
        "duree": 256,
        "id": "KOOhPfMbuIQ",
        "titre": "half•alive - still feel. [OFFICIAL VIDEO]",
        "playlist": "CHARLY-RADIO (77 titres)",
        "start_minute": 781.2833333333335
    },
    {
        "duree": 92,
        "id": "iQGAPewPH1s",
        "playlist": "Charly-JPOP",
        "titre": "『僕のヒーローアカデミア』ヒロアカ2期第1クールノンクレジットオープニング映像／OPテーマ：「ピースサイン」米津玄師／ヒロアカOP",
        "start_minute": 785.5500000000002
    },
    {
        "duree": 238,
        "id": "t-6vQLdz6C8",
        "playlist": "Charly-JPOP",
        "titre": "Merry Go Round",
        "start_minute": 787.0833333333335
    },
    {
        "duree": 236,
        "id": "aSugSGCC12I",
        "playlist": "Charly-RapPop",
        "titre": "Sabrina Carpenter - Manchild (Official Video)",
        "start_minute": 791.0500000000002
    },
    {
        "duree": 147,
        "id": "Zc_c36jJ40I",
        "playlist": "Charly-RapPop",
        "titre": "Lorenzo - Nique la BAC (prod. Le Poto Rico)",
        "start_minute": 794.9833333333335
    },
    {
        "duree": 185,
        "id": "lukT_WB5IB0",
        "playlist": "Charly-RapPop",
        "titre": "Yamê - Bécane | A COLORS SHOW",
        "start_minute": 797.4333333333335
    },
    {
        "duree": 100,
        "id": "wbQEA_nxLaE",
        "playlist": "Charly-JPOP",
        "titre": "BOCCHI THE ROCK! - Ending | Distortion!!",
        "start_minute": 800.5166666666669
    },
    {
        "duree": 247,
        "id": "56STvMBKYdw",
        "playlist": "Charly-RapPop",
        "titre": "Damso - 911 [Clip Officiel]",
        "start_minute": 802.1833333333335
    },
    {
        "duree": 253,
        "id": "oGdhZyS2ozo",
        "playlist": "Charly-RapPop",
        "titre": "OrelSan - La Terre est Ronde [VIDÉO OFFICIELLE]",
        "start_minute": 806.3000000000002
    },
    {
        "duree": 206,
        "id": "B_1moEBS4TE",
        "playlist": "CHARLY-LOVE",
        "titre": "Hate It Or Love It",
        "start_minute": 810.5166666666669
    },
    {
        "duree": 201,
        "id": "zl-S7piEp_U",
        "playlist": "CHARLY-LOVE",
        "titre": "Wildest Dreams",
        "start_minute": 813.9500000000002
    },
    {
        "duree": 166,
        "id": "WdzRZt-srpY",
        "playlist": "CHARLY-GROOVE",
        "titre": "Deep Down",
        "start_minute": 817.3000000000002
    },
    {
        "duree": 233,
        "id": "esqRBsVumrw",
        "titre": "Jungle - Candle Flame (feat. Erick The Architect) (Official Video)",
        "playlist": "CHARLY-RADIO (77 titres)",
        "start_minute": 820.0666666666668
    },
    {
        "duree": 190,
        "id": "l446hUqQ7GY",
        "playlist": "Charly-JPOP",
        "titre": "ATARASHII GAKKO! - オトナブルー (Official Music Video)",
        "start_minute": 823.9500000000002
    },
    {
        "duree": 208,
        "id": "dy90tA3TT1c",
        "playlist": "Charly-JPOP",
        "titre": "YOASOBI「怪物」Official Music Video　(YOASOBI - Monster)",
        "start_minute": 827.1166666666668
    },
    {
        "duree": 328,
        "id": "tLsJQ5srVQA",
        "playlist": "Charly-JPOP",
        "titre": "ALI - LOST IN PARADISE feat. AKLO（Re-edit ver.）",
        "start_minute": 830.5833333333335
    },
    {
        "duree": 181,
        "id": "TnbSasaBnZ8",
        "playlist": "CHARLY-LOVE",
        "titre": "Yu Yu Hakusho Romantic Theme Slowed & Reverbed (Remix)",
        "start_minute": 836.0500000000002
    },
    {
        "duree": 150,
        "id": "Wgw6tJ8yz9M",
        "titre": "JAWNY - Honeypie (Official Video)",
        "playlist": "CHARLY-RADIO (77 titres)",
        "start_minute": 840.0
    },
    {
        "duree": 107,
        "id": "YXexSXix3zs",
        "playlist": "Charly-JPOP",
        "titre": "JoJo: ★ STEEL BALL RUN OP ★『Holy Steel』- Original - JoJo's Bizarre Adventure Part 7 【ジョジョの奇妙な冒険】",
        "start_minute": 842.5
    },
    {
        "duree": 96,
        "id": "jlwOlzVK5kY",
        "playlist": "Charly-JPOP",
        "titre": "『僕のヒーローアカデミア』5期第1クールノンクレジットオープニング映像／OPテーマ:「No.1」DISH//／ヒロアカOP",
        "start_minute": 844.2833333333333
    },
    {
        "duree": 306,
        "id": "1p2-O2jVhPU",
        "titre": "Guts - Come Closer (Official Audio)",
        "playlist": "CHARLY-RADIO (77 titres)",
        "start_minute": 845.8833333333333
    },
    {
        "duree": 70,
        "id": "uYXNN3jlgJ4",
        "playlist": "Charly-RapPop",
        "titre": "BLOKAMIL",
        "start_minute": 850.9833333333333
    },
    {
        "duree": 125,
        "id": "BQ-v0bU9C5g",
        "playlist": "Charly-JPOP",
        "titre": "JoJo's Bizarre Adventure - Opening 9 v1 [4K 60FPS | Creditless | CC]",
        "start_minute": 852.15
    },
    {
        "duree": 159,
        "id": "PV8Sw6XsDEg",
        "playlist": "Charly-RapPop",
        "titre": "Lorenzo - Catastrophe (Clip Officiel)",
        "start_minute": 854.2333333333333
    },
    {
        "duree": 147,
        "id": "F2YpXC1itEE",
        "playlist": "Charly-RapPop",
        "titre": "Pedro Pedro Pedro - Racoon Meme Full Version",
        "start_minute": 856.8833333333333
    },
    {
        "duree": 188,
        "id": "euYS4ldiMjc",
        "playlist": "CHARLY-HOUSE",
        "titre": "Bad Boy",
        "start_minute": 859.3333333333334
    },
    {
        "duree": 215,
        "id": "3cKtSlsYVEU",
        "playlist": "CHARLY-GROOVE",
        "titre": "September",
        "start_minute": 862.4666666666667
    },
    {
        "duree": 438,
        "id": "6POZlJAZsok",
        "playlist": "CHARLY-LOVE",
        "titre": "Just the Two of Us (feat. Bill Withers)",
        "start_minute": 866.0500000000001
    },
    {
        "duree": 244,
        "id": "VZkRAp9XMIg",
        "playlist": "CHARLY-LOVE",
        "titre": "Cosmic Girl (Remastered 2013)",
        "start_minute": 873.35
    },
    {
        "duree": 176,
        "id": "O2tKlnfrLkY",
        "playlist": "Charly-RapPop",
        "titre": "melodrama",
        "start_minute": 877.4166666666667
    },
    {
        "duree": 234,
        "id": "02nFGcia31M",
        "playlist": "CHARLY-LOVE",
        "titre": "Casio",
        "start_minute": 880.35
    },
    {
        "duree": 198,
        "id": "yAoPhl4LaWg",
        "playlist": "Charly_Remix",
        "titre": "Kaaris x VIDEO CLUB - ROI DE SEVRAN",
        "start_minute": 884.25
    },
    {
        "duree": 123,
        "id": "nzOaH0YGqb0",
        "playlist": "Charly-JPOP",
        "titre": "JoJo's Bizarre Adventure - Opening 4 v1 [4K 60FPS | Creditless | CC]",
        "start_minute": 887.55
    },
    {
        "duree": 154,
        "id": "nZcTVkXJV1o",
        "playlist": "Charly-RapPop",
        "titre": "Gambi - MACINTOSH (Clip officiel)",
        "start_minute": 889.5999999999999
    },
    {
        "duree": 194,
        "id": "ByHxaDIyRTk",
        "playlist": "Charly-RapPop",
        "titre": "Jul - JCVD // Clip Officiel // 2019",
        "start_minute": 892.1666666666666
    },
    {
        "duree": 132,
        "id": "2Px16OD1qcU",
        "playlist": "Charly-RapPop",
        "titre": "bbno$ - bing bong (feat. VNLLA)",
        "start_minute": 895.4
    },
    {
        "duree": 246,
        "id": "GsYzuUt_QPE",
        "playlist": "Charly-RapPop",
        "titre": "Jimmy Punchline",
        "start_minute": 897.6
    },
    {
        "duree": 188,
        "id": "XqJosdWocto",
        "playlist": "CHARLY-LOVE",
        "titre": "Moonlight",
        "start_minute": 901.7
    },
    {
        "duree": 128,
        "id": "tDgn9PwjTXw",
        "playlist": "Charly_Remix",
        "titre": "LA FÈVE - MAUVAIS PAYEUR - DISCO REMIX (Give Me The Night)",
        "start_minute": 904.8333333333334
    },
    {
        "duree": 90,
        "id": "gcgKUcJKxIs",
        "playlist": "Charly-JPOP",
        "titre": "TVアニメ『呪術廻戦』第2期「懐玉・玉折」ノンクレジットOPムービー／OPテーマ：キタニタツヤ「青のすみか」｜毎週木曜夜11時56分～MBS/TBS系列全国28局にて放送中!!",
        "start_minute": 906.9666666666667
    },
    {
        "duree": 255,
        "id": "1zwaZkOXXqw",
        "playlist": "CHARLY-GROOVE",
        "titre": "Daddy ! Daddy ! Do !",
        "start_minute": 908.4666666666667
    },
    {
        "duree": 164,
        "id": "dybNNo8y48k",
        "titre": "Breakbot - Another You (Feat. Ruckazoid) [Official Video]",
        "playlist": "CHARLY-RADIO (77 titres)",
        "start_minute": 912.7166666666667
    },
    {
        "duree": 102,
        "id": "AhNYcpN1pEU",
        "playlist": "Charly-JPOP",
        "titre": "DAN DA DAN Season 2 ED | Doukashiteru by WurtS | Netflix Anime",
        "start_minute": 915.45
    },
    {
        "duree": 168,
        "id": "8sIJNHn1uyc",
        "playlist": "Charly_Remix",
        "titre": "i kissed a girl (hardstyle)",
        "start_minute": 917.1500000000001
    },
    {
        "duree": 224,
        "id": "B5JltVIgEmk",
        "playlist": "Charly_Remix",
        "titre": "Kaaris x Dark Soul - L'empereur de Sevran",
        "start_minute": 919.95
    },
    {
        "duree": 191,
        "id": "JT0MFh1TqMI",
        "playlist": "CHARLY-HOUSE",
        "titre": "Leurs Bails",
        "start_minute": 923.6833333333334
    },
    {
        "duree": 167,
        "id": "jj88i2vhdcg",
        "playlist": "Charly-RapPop",
        "titre": "Vladimir Cauchemar & Vald - Elévation (Official Music Video)",
        "start_minute": 926.8666666666667
    },
    {
        "duree": 308,
        "id": "QBTJf1txjC4",
        "playlist": "CHARLY-GROOVE",
        "titre": "Got to Be Real",
        "start_minute": 929.65
    },
    {
        "duree": 222,
        "id": "xk1c02v3U_U",
        "playlist": "Charly-RapPop",
        "titre": "Ziak - Fixette (Prod. Focus Beatz)",
        "start_minute": 934.7833333333333
    },
    {
        "duree": 121,
        "id": "qm1EaIp_s2w",
        "playlist": "Charly-JPOP",
        "titre": "Jujutsu Kaisen Season 3 OP / Opening 1 – 4K | 24FPS | Lyrics",
        "start_minute": 938.4833333333333
    },
    {
        "duree": 272,
        "id": "szy_L1-16wg",
        "playlist": "Charly-JPOP",
        "titre": "September",
        "start_minute": 940.5
    },
    {
        "duree": 338,
        "id": "20OGm_-RebE",
        "playlist": "CHARLY-GROOVE",
        "titre": "Hung Up",
        "start_minute": 945.0333333333333
    },
    {
        "duree": 146,
        "id": "8hAS7PWdgVE",
        "playlist": "Charly-RapPop",
        "titre": "Chic type",
        "start_minute": 950.6666666666666
    },
    {
        "duree": 130,
        "id": "m7jfM9A6R-k",
        "playlist": "Charly-RapPop",
        "titre": "Vladimir Cauchemar & 6IX9INE \"Aulos Reloaded\" (WSHH Exclusive - Official Music Video)",
        "start_minute": 953.0999999999999
    },
    {
        "duree": 343,
        "id": "QNYT9wVwQ8A",
        "playlist": "Charly-JPOP",
        "titre": "Miki Matsubara - Stay With Me HD (Club Mix)",
        "start_minute": 955.2666666666665
    },
    {
        "duree": 203,
        "id": "CEw-7cMnBDY",
        "titre": "Bruno Mars, Anderson .Paak, Silk Sonic - Skate [Official Music Video]",
        "playlist": "CHARLY-RADIO (77 titres)",
        "start_minute": 960.9833333333332
    },
    {
        "duree": 379,
        "id": "ndEhXtwoOmQ",
        "playlist": "CHARLY-GROOVE",
        "titre": "Daddy Sweet",
        "start_minute": 964.3666666666666
    },
    {
        "duree": 173,
        "id": "O_n_0whrgWc",
        "playlist": "CHARLY-GROOVE",
        "titre": "WO:OO",
        "start_minute": 970.6833333333333
    },
    {
        "duree": 170,
        "id": "DiTd771WumE",
        "playlist": "CHARLY-GROOVE",
        "titre": "APT.",
        "start_minute": 973.5666666666666
    },
    {
        "duree": 255,
        "id": "bgmMpT_m-t4",
        "playlist": "CHARLY-GROOVE",
        "titre": "Part-Time Lover",
        "start_minute": 976.4
    },
    {
        "duree": 206,
        "id": "sn0viUbmUVU",
        "playlist": "CHARLY-GROOVE",
        "titre": "Standing Next to You",
        "start_minute": 980.65
    },
    {
        "duree": 185,
        "id": "GFjJ11WZS2Y",
        "playlist": "CHARLY-GROOVE",
        "titre": "You & Me",
        "start_minute": 984.0833333333333
    },
    {
        "duree": 328,
        "id": "4qqeafI9kXM",
        "playlist": "CHARLY-GROOVE",
        "titre": "LOST IN PARADISE (Jujutsu Kaisen Ending Theme Song)",
        "start_minute": 987.1666666666666
    },
    {
        "duree": 174,
        "id": "FlDuQhsxLms",
        "playlist": "CHARLY-GROOVE",
        "titre": "Candle Flame",
        "start_minute": 992.6333333333333
    },
    {
        "duree": 288,
        "id": "OLZga32cQNo",
        "playlist": "CHARLY-GROOVE",
        "titre": "1979",
        "start_minute": 995.5333333333333
    },
    {
        "duree": 248,
        "id": "zYV6zZc_9jI",
        "playlist": "CHARLY-GROOVE",
        "titre": "Give It To Me Baby",
        "start_minute": 1000.3333333333333
    },
    {
        "duree": 175,
        "id": "kIft-LUHHVA",
        "playlist": "CHARLY-GROOVE",
        "titre": "Espresso",
        "start_minute": 1004.4666666666666
    },
    {
        "duree": 237,
        "id": "fWlvNwdAoAc",
        "playlist": "CHARLY-GROOVE",
        "titre": "Cloud 9",
        "start_minute": 1007.3833333333332
    },
    {
        "duree": 104,
        "id": "Gzuk7oK7ngE",
        "playlist": "CHARLY-GROOVE",
        "titre": "反面教師",
        "start_minute": 1011.3333333333333
    },
    {
        "duree": 283,
        "id": "L1_PRGs6OYI",
        "playlist": "CHARLY-GROOVE",
        "titre": "Tondoho Mba",
        "start_minute": 1013.0666666666666
    },
    {
        "duree": 294,
        "id": "Kr4EQDVETuA",
        "playlist": "CHARLY-GROOVE",
        "titre": "Billie Jean",
        "start_minute": 1017.7833333333333
    },
    {
        "duree": 235,
        "id": "4JkIs37a2JE",
        "titre": "Jamiroquai - Virtual Insanity (Official Video)",
        "playlist": "CHARLY-RADIO (77 titres)",
        "start_minute": 1022.6833333333333
    },
    {
        "duree": 259,
        "id": "zikd5BZycZQ",
        "playlist": "CHARLY-GROOVE",
        "titre": "Do It",
        "start_minute": 1026.6
    },
    {
        "duree": 278,
        "id": "bzb2He1C_UU",
        "playlist": "CHARLY-GROOVE",
        "titre": "Get on the Floor",
        "start_minute": 1030.9166666666665
    },
    {
        "duree": 240,
        "id": "qXI87eMP-bs",
        "playlist": "CHARLY-GROOVE",
        "titre": "Face to Face",
        "start_minute": 1035.55
    },
    {
        "duree": 195,
        "id": "RBR1DFcyqgY",
        "playlist": "CHARLY-GROOVE",
        "titre": "Welcome To The Disco",
        "start_minute": 1039.55
    },
    {
        "duree": 93,
        "id": "bzNXDsfqfVs",
        "playlist": "Charly-JPOP",
        "titre": "『僕のヒーローアカデミア』6期第2クールノンクレジットオープニング映像／OPテーマ：「ぼくらの」Eve／ヒロアカOP",
        "start_minute": 1042.8
    },
    {
        "duree": 206,
        "id": "1KN4DhVXw-Y",
        "playlist": "Charly-JPOP",
        "titre": "yama - a.m.3:21 (Official Video)",
        "start_minute": 1044.35
    },
    {
        "duree": 99,
        "id": "BHf7fe-pxbU",
        "playlist": "Charly-JPOP",
        "titre": "Zom 100: Bucket List of The Dead - Opening | Song of the Dead",
        "start_minute": 1047.7833333333333
    },
    {
        "duree": 297,
        "id": "22tVWwmTie8",
        "playlist": "Charly-RapPop",
        "titre": "Eminem - Houdini [Official Music Video]",
        "start_minute": 1049.4333333333334
    },
    {
        "duree": 255,
        "id": "tvNSXS4x9nc",
        "playlist": "Charly-RapPop",
        "titre": "Kendrick Lamar - United In Grief (Official Audio)",
        "start_minute": 1054.3833333333334
    },
    {
        "duree": 310,
        "id": "rtL5oMyBHPs",
        "playlist": "Charly-RapPop",
        "titre": "MGMT - Little Dark Age (Official Video)",
        "start_minute": 1058.6333333333334
    },
    {
        "duree": 245,
        "id": "h-Fzs4M_hAY",
        "playlist": "Charly_Remix",
        "titre": "GIVE ME LA PRISE CONNECTÉE",
        "start_minute": 1063.8000000000002
    },
    {
        "duree": 222,
        "id": "L0qBulm0hbg",
        "playlist": "CHARLY-LOVE",
        "titre": "I Keep Forgettin' (Every Time You're Near)",
        "start_minute": 1067.8833333333334
    },
    {
        "duree": 244,
        "id": "SunvrwYCvpU",
        "playlist": "CHARLY-HOUSE",
        "titre": "Cowboy Bebop - Tank! (Bass Cover) (Play Along Tabs In Video)",
        "start_minute": 1071.5833333333335
    },
    {
        "duree": 223,
        "id": "lIIyA3DAQXo",
        "playlist": "Charly-RapPop",
        "titre": "Changement [CLIP OFFICIEL]",
        "start_minute": 1075.65
    },
    {
        "duree": 265,
        "id": "FxzBvqY5PP0",
        "titre": "Daft Punk - Digital Love (Official Video)",
        "playlist": "CHARLY-RADIO (77 titres)",
        "start_minute": 1080.0
    },
    {
        "duree": 210,
        "id": "PHW3GmSPwzU",
        "playlist": "CHARLY-HOUSE",
        "titre": "NIGHT DANCER (BIG Naughty Remix)",
        "start_minute": 1084.4166666666667
    },
    {
        "duree": 242,
        "id": "N0TA8xXWSqE",
        "playlist": "CHARLY-HOUSE",
        "titre": "Smooth Operator - TikTok Remix",
        "start_minute": 1087.9166666666667
    },
    {
        "duree": 174,
        "id": "tkrdvrf0W-k",
        "playlist": "Charly-RapPop",
        "titre": "OrelSan - Encore une fois (feat. Yamê) [CLIP OFFICIEL]",
        "start_minute": 1091.95
    },
    {
        "duree": 206,
        "id": "X6MxGJ7qxck",
        "playlist": "Charly-RapPop",
        "titre": "JUL - WESH ALORS // CLIP OFFICIEL //2015",
        "start_minute": 1094.8500000000001
    },
    {
        "duree": 236,
        "id": "onhBN0qkUcE",
        "playlist": "Charly-JPOP",
        "titre": "花占い / Vaundy：MUSIC VIDEO",
        "start_minute": 1098.2833333333335
    },
    {
        "duree": 244,
        "id": "DZiaXEIQgkE",
        "playlist": "Charly-RapPop",
        "titre": "Salvatore Ganacci - Fight Dirty",
        "start_minute": 1102.216666666667
    },
    {
        "duree": 189,
        "id": "mkiVLIkotwk",
        "playlist": "Charly-RapPop",
        "titre": "Orelsan - Boss (lyrics video)",
        "start_minute": 1106.2833333333335
    },
    {
        "duree": 271,
        "id": "5TqetBMBTww",
        "playlist": "Charly-RapPop",
        "titre": "Angèle - Démons feat. Damso [OFFICIAL MUSIC VIDEO]",
        "start_minute": 1109.4333333333336
    },
    {
        "duree": 167,
        "id": "4g_bq5pRXYs",
        "playlist": "Charly-RapPop",
        "titre": "Tony Hawk",
        "start_minute": 1113.9500000000003
    },
    {
        "duree": 95,
        "id": "FNgZ72EV9ls",
        "playlist": "Charly-JPOP",
        "titre": "『僕のヒーローアカデミア』3期第1クールノンクレジットオープニング映像／OPテーマ：「ODD FUTURE」UVERworld／ヒロアカOP",
        "start_minute": 1116.7333333333336
    },
    {
        "duree": 170,
        "id": "OAq4t0n1rkY",
        "playlist": "Charly-RapPop",
        "titre": "Lorenzo - Bizness (Clip Officiel)",
        "start_minute": 1118.3166666666668
    },
    {
        "duree": 242,
        "id": "Ic5vxw3eijY",
        "playlist": "Charly-RapPop",
        "titre": "Estelle - American Boy [Feat. Kanye West] [Video]",
        "start_minute": 1121.15
    },
    {
        "duree": 216,
        "id": "GGhKPm18E48",
        "playlist": "Charly-RapPop",
        "titre": "Damso - Θ. Macarena (Clip Officiel)",
        "start_minute": 1125.1833333333334
    },
    {
        "duree": 255,
        "id": "ZUwaudw8ht0",
        "playlist": "Charly-JPOP",
        "titre": "ずっと真夜中でいいのに。『あいつら全員同窓会』MV (ZUTOMAYO - Inside Joke)",
        "start_minute": 1128.7833333333333
    },
    {
        "duree": 367,
        "id": "fe4EK4HSPkI",
        "playlist": "Charly-RapPop",
        "titre": "MGMT - Kids (Official HD Video)",
        "start_minute": 1133.0333333333333
    },
    {
        "duree": 155,
        "id": "6okxuiiHx2w",
        "titre": "Breakbot - Baby I'm Yours (feat. Irfane) [Official Video]",
        "playlist": "CHARLY-RADIO (77 titres)",
        "start_minute": 1140.0
    },
    {
        "duree": 200,
        "id": "Zr93W_omd4M",
        "playlist": "Charly-RapPop",
        "titre": "Little Big x bbno$ - IT HAPPENS (Official Music Video)",
        "start_minute": 1142.5833333333333
    },
    {
        "duree": 204,
        "id": "2gWTxnj0pJs",
        "playlist": "Charly-JPOP",
        "titre": "ENDEAVOR'S THEME (Endeavor vs Nomu Version) MHA S4 Ost",
        "start_minute": 1145.9166666666665
    },
    {
        "duree": 96,
        "id": "MdfFVdFWl1U",
        "playlist": "Charly-JPOP",
        "titre": "『僕のヒーローアカデミア』4期第クール「文化祭編」ノンクレジットOP映像／OPテーマ：「スターマーカー」KANA-BOON／ヒロアカOP",
        "start_minute": 1149.3166666666666
    },
    {
        "duree": 291,
        "id": "g3jCAyPai2Y",
        "playlist": "Charly-JPOP",
        "titre": "Yakuza OST - Baka Mitai (ばかみたい) Kiryu full version",
        "start_minute": 1150.9166666666665
    },
    {
        "duree": 109,
        "id": "_bet3SF1xbM",
        "playlist": "Charly-RapPop",
        "titre": "Flow externe",
        "start_minute": 1155.7666666666664
    },
    {
        "duree": 217,
        "id": "iXzBdNjpYw0",
        "playlist": "Charly-RapPop",
        "titre": "OrelSan - Rêves bizarres (feat. Damso) [CLIP OFFICIEL]",
        "start_minute": 1157.583333333333
    },
    {
        "duree": 177,
        "id": "rE36juT-NVg",
        "playlist": "CHARLY-LOVE",
        "titre": "Everything Eventually Ends",
        "start_minute": 1161.1999999999996
    },
    {
        "duree": 238,
        "id": "UPnMFUsKm8w",
        "playlist": "Charly-RapPop",
        "titre": "Kalash - Mwaka Moon ft. Damso",
        "start_minute": 1164.1499999999996
    },
    {
        "duree": 265,
        "id": "dlFA0Zq1k2A",
        "playlist": "Charly-JPOP",
        "titre": "KANA-BOON - Silhouette",
        "start_minute": 1168.1166666666663
    },
    {
        "duree": 269,
        "id": "NwIxIAztiag",
        "playlist": "Charly-RapPop",
        "titre": "Népal - Rien d'Spécial #LaxVision",
        "start_minute": 1172.533333333333
    },
    {
        "duree": 263,
        "id": "GtUVQei3nX4",
        "playlist": "Charly-RapPop",
        "titre": "Snoop Dogg - Drop It Like It's Hot (Official Music Video) ft. Pharrell Williams",
        "start_minute": 1177.0166666666664
    },
    {
        "duree": 94,
        "id": "l2j1qM7gx54",
        "playlist": "Charly-JPOP",
        "titre": "『僕のヒーローアカデミア』2期第2クールオープニング映像／OPテーマ：「空に歌えば」amazarashi／ヒロアカOP",
        "start_minute": 1181.3999999999999
    },
    {
        "duree": 119,
        "id": "aDgst6m_Stg",
        "playlist": "Charly_Remix",
        "titre": "JuL JCVD X I Follow rivers (Remix)",
        "start_minute": 1182.9666666666665
    },
    {
        "duree": 298,
        "id": "YVkUvmDQ3HY",
        "playlist": "Charly-RapPop",
        "titre": "Eminem - Without Me (Official Music Video)",
        "start_minute": 1184.9499999999998
    },
    {
        "duree": 251,
        "id": "GGz3yRFCqUY",
        "playlist": "Charly_Remix",
        "titre": "Kaaris x Evangelion - Bouchon de liège (remix)",
        "start_minute": 1189.9166666666665
    },
    {
        "duree": 253,
        "id": "KMdTrqzEI0I",
        "playlist": "CHARLY-LOVE",
        "titre": "恋",
        "start_minute": 1194.1
    },
    {
        "duree": 157,
        "id": "ZZ99I2Gw-V0",
        "playlist": "CHARLY-TROPIQUES",
        "titre": "Passionfruit",
        "start_minute": 1198.3166666666666
    },
    {
        "duree": 90,
        "id": "faqmNf_fZlE",
        "playlist": "Charly-JPOP",
        "titre": "Hunter X Hunter Opening 1 | Departure!",
        "start_minute": 1200.9333333333332
    },
    {
        "duree": 179,
        "id": "9eJsDDvpwmE",
        "playlist": "Charly-RapPop",
        "titre": "Hamza - God Bless feat. Damso (Clip officiel)",
        "start_minute": 1202.4333333333332
    },
    {
        "duree": 123,
        "id": "eFxVmnNydx4",
        "playlist": "Charly-JPOP",
        "titre": "JoJo's Bizarre Adventure - Opening 10 v1 [4K 60FPS | Creditless | CC]",
        "start_minute": 1205.4166666666665
    },
    {
        "duree": 372,
        "id": "48gaaQfS9lc",
        "playlist": "Charly_Remix",
        "titre": "(REMASTERED) Daft Punk - Veridis Quo x The Weeknd - In Your Eyes",
        "start_minute": 1207.4666666666665
    },
    {
        "duree": 180,
        "id": "9U4-PgbN7eM",
        "playlist": "CHARLY-LOVE",
        "titre": "LUNCH",
        "start_minute": 1213.6666666666665
    },
    {
        "duree": 383,
        "id": "QzoBB9NO9Dc",
        "playlist": "Charly-RapPop",
        "titre": "Mafia K'1 Fry - Pour ceux (Clip officiel)",
        "start_minute": 1216.6666666666665
    },
    {
        "duree": 109,
        "id": "AQ3oyp4D6FY",
        "playlist": "Charly-JPOP",
        "titre": "JoJo's Bizarre Adventure - Opening 5 v1 [4K 60FPS | Creditless | CC]",
        "start_minute": 1223.05
    },
    {
        "duree": 178,
        "id": "QuvqzlxEO6g",
        "playlist": "Charly-RapPop",
        "titre": "bbno$ - it boy (official music video)",
        "start_minute": 1224.8666666666666
    },
    {
        "duree": 282,
        "id": "vk6014HuxcE",
        "playlist": "Charly-RapPop",
        "titre": "JAŸ-Z - Empire State Of Mind ft. Alicia Keys",
        "start_minute": 1227.8333333333333
    },
    {
        "duree": 309,
        "id": "T_lC2O1oIew",
        "playlist": "Charly-JPOP",
        "titre": "竹内まりや -  Plastic Love (Official Music Video)",
        "start_minute": 1232.5333333333333
    },
    {
        "duree": 124,
        "id": "wPdX66-Ag2s",
        "playlist": "Charly-JPOP",
        "titre": "JoJo's Bizarre Adventure - Opening 1 [4K 60FPS | Creditless | CC]",
        "start_minute": 1237.6833333333334
    },
    {
        "duree": 197,
        "id": "e5s8MdtnbMM",
        "playlist": "Charly-RapPop",
        "titre": "Angèle - What You Want (feat. Justice) (Official Video)",
        "start_minute": 1239.75
    },
    {
        "duree": 243,
        "id": "9i6tf3gIcfM",
        "playlist": "CHARLY-LOVE",
        "titre": "Can't Get Enough Of Your Love, Babe",
        "start_minute": 1243.0333333333333
    },
    {
        "duree": 207,
        "id": "vgOTxZtlXys",
        "playlist": "CHARLY-LOVE",
        "titre": "After The Storm",
        "start_minute": 1247.0833333333333
    },
    {
        "duree": 163,
        "id": "g9bRUY3znnA",
        "playlist": "Charly-RapPop",
        "titre": "boom",
        "start_minute": 1250.5333333333333
    },
    {
        "duree": 147,
        "id": "s1At5s0YLSs",
        "playlist": "Charly-RapPop",
        "titre": "miki - ça pik un peu quand même",
        "start_minute": 1253.25
    },
    {
        "duree": 153,
        "id": "Im8cHCP5cVE",
        "playlist": "Charly-RapPop",
        "titre": "bbno$ & Yung Gravy (BABY GRAVY) - Super Smash Bro's (Visualizer)",
        "start_minute": 1255.7
    },
    {
        "duree": 164,
        "id": "dybNNo8y48k",
        "titre": "Breakbot - Another You (Feat. Ruckazoid) [Official Video]",
        "playlist": "CHARLY-RADIO (77 titres)",
        "start_minute": 1260.0
    },
    {
        "duree": 94,
        "id": "YEKboKtPx-w",
        "playlist": "Charly-JPOP",
        "titre": "『僕のヒーローアカデミア』ヒロアカ7期OPノンクレジット映像／OPテーマ：「誰我為」TK from 凛として時雨／My Heroacademia 7th season Opening Movie",
        "start_minute": 1262.7333333333333
    },
    {
        "duree": 234,
        "id": "ItyyFwwRWaQ",
        "playlist": "CHARLY-TROPIQUES",
        "titre": "Groove ma poule",
        "start_minute": 1264.3
    },
    {
        "duree": 175,
        "id": "2j8ALtAxOjE",
        "playlist": "Charly-RapPop",
        "titre": "bbno$ - come to brazil (official music video)",
        "start_minute": 1268.2
    },
    {
        "duree": 258,
        "id": "SiAuAJBZuGs",
        "playlist": "Charly-RapPop",
        "titre": "Tessa Violet - Crush (Official Music Video)",
        "start_minute": 1271.1166666666668
    },
    {
        "duree": 95,
        "id": "WUDWBg4cFiw",
        "playlist": "Charly-JPOP",
        "titre": "『僕のヒーローアカデミア』3期第2クールノンクレジットオープニング映像／OPテーマ：「Make my story」Lenny code fiction／ヒロアカOP",
        "start_minute": 1275.4166666666667
    },
    {
        "duree": 134,
        "id": "eqjFmsZGBSc",
        "playlist": "Charly-JPOP",
        "titre": "Kaguya-sama: Love is War Ending 2 (4k 60FPS)┃Creditless",
        "start_minute": 1277.0
    },
    {
        "duree": 256,
        "id": "SDTZ7iX4vTQ",
        "playlist": "Charly-RapPop",
        "titre": "Foster The People - Pumped Up Kicks (Official Video)",
        "start_minute": 1279.2333333333333
    },
    {
        "duree": 198,
        "id": "KEG7b851Ric",
        "playlist": "Charly-RapPop",
        "titre": "Sabrina Carpenter - Taste (Official Video)",
        "start_minute": 1283.5
    },
    {
        "duree": 151,
        "id": "k9MikbjSR5M",
        "playlist": "Charly-RapPop",
        "titre": "Lorenzo - Fonsdé Toute La Night (Clip Officiel)",
        "start_minute": 1286.8
    },
    {
        "duree": 119,
        "id": "7OXULEBUpOg",
        "playlist": "Charly-RapPop",
        "titre": "Ziak - Raspoutine (Prod. Jango)",
        "start_minute": 1289.3166666666666
    },
    {
        "duree": 100,
        "id": "dlSbEP4V-gI",
        "playlist": "Charly-JPOP",
        "titre": "BOCCHI THE ROCK! - Opening | Seishun Complex",
        "start_minute": 1291.3
    },
    {
        "duree": 100,
        "id": "epZaT8B31-g",
        "playlist": "Charly-JPOP",
        "titre": "Mob Psycho 100 II Opening | 99.9 by Mob Choir",
        "start_minute": 1292.9666666666667
    },
    {
        "duree": 254,
        "id": "507d9xto6Og",
        "playlist": "Charly-RapPop",
        "titre": "Gringe - Qui dit mieux (feat. OrelSan, Vald, Suikon Blaz AD) [ENFANT LUNE]",
        "start_minute": 1294.6333333333334
    },
    {
        "duree": 141,
        "id": "K6BRna4_bmg",
        "titre": "bbno$ & Rich Brian - edamame (Official Video)",
        "playlist": "CHARLY-RADIO (77 titres)",
        "start_minute": 1298.8666666666668
    },
    {
        "duree": 224,
        "id": "QG_yHZDlFqE",
        "playlist": "Charly-RapPop",
        "titre": "OrelSan - Du propre [CLIP OFFICIEL]",
        "start_minute": 1301.2166666666667
    },
    {
        "duree": 270,
        "id": "4riRG2N0868",
        "playlist": "Charly_Remix",
        "titre": "Kaaris - Je BiBi (Phonk Remix)",
        "start_minute": 1304.95
    },
    {
        "duree": 185,
        "id": "9cHbvRUALrc",
        "playlist": "CHARLY-LOVE",
        "titre": "Pink + White",
        "start_minute": 1309.45
    },
    {
        "duree": 186,
        "id": "H_rZMgS5nE4",
        "playlist": "Charly-RapPop",
        "titre": "Gambi - POPOPOP (Clip officiel)",
        "start_minute": 1312.5333333333333
    },
    {
        "duree": 257,
        "id": "eS_korRhTDk",
        "playlist": "Charly-RapPop",
        "titre": "Lemaitre - Closer (UK Version) ft. Jennie A.",
        "start_minute": 1315.6333333333332
    },
    {
        "duree": 167,
        "id": "nmbiBVPe5bY",
        "playlist": "Charly_K-pop",
        "titre": "Strategy",
        "start_minute": 1319.9166666666665
    },
    {
        "duree": 222,
        "id": "uscYtbTNdtQ",
        "playlist": "Charly_Remix",
        "titre": "KAARIS X JOJO - SE-VRAK (PHONK REMIX)",
        "start_minute": 1322.6999999999998
    },
    {
        "duree": 181,
        "id": "VuCLlilNjkM",
        "playlist": "Charly_Remix",
        "titre": "NISKA ft. 1PLIKÉ140 - 140G 90's REMIX (Can't Touch This)",
        "start_minute": 1326.3999999999999
    },
    {
        "duree": 265,
        "id": "AW1ssZ5w79k",
        "playlist": "CHARLY-TROPIQUES",
        "titre": "Marechià",
        "start_minute": 1329.4166666666665
    },
    {
        "duree": 172,
        "id": "S9BTi5ep8Ao",
        "playlist": "Charly-RapPop",
        "titre": "Vladimir Cauchemar BRRR feat. Laylow, Rim'K & Asdek",
        "start_minute": 1333.8333333333333
    },
    {
        "duree": 156,
        "id": "X-28YDdooCI",
        "playlist": "Charly_Remix",
        "titre": "Kendrick Lamar - M.A.A.D City (Brawl Remix with choir)",
        "start_minute": 1336.6999999999998
    },
    {
        "duree": 107,
        "id": "dXhbXgeLpSc",
        "playlist": "Charly-JPOP",
        "titre": "JoJo's Bizarre Adventure - Opening 6 [4K 60FPS | Creditless | CC]",
        "start_minute": 1339.2999999999997
    },
    {
        "duree": 122,
        "id": "Q_2cChbDg4I",
        "playlist": "Charly-RapPop",
        "titre": "DA7 - 777",
        "start_minute": 1341.083333333333
    },
    {
        "duree": 434,
        "id": "dIlUbb4VtzY",
        "titre": "Michael Jackson- Rock with you (The Reflex Revision)",
        "playlist": "CHARLY-RADIO (77 titres)",
        "start_minute": 1343.1166666666663
    },
    {
        "duree": 198,
        "id": "KTNMbj_Ns7Y",
        "playlist": "Charly_Remix",
        "titre": "U CAN'T TOUCH KOBA",
        "start_minute": 1350.3499999999997
    },
    {
        "duree": 191,
        "id": "JT0MFh1TqMI",
        "playlist": "CHARLY-HOUSE",
        "titre": "Leurs Bails",
        "start_minute": 1353.6499999999996
    },
    {
        "duree": 188,
        "id": "euYS4ldiMjc",
        "playlist": "CHARLY-HOUSE",
        "titre": "Bad Boy",
        "start_minute": 1356.833333333333
    },
    {
        "duree": 244,
        "id": "SunvrwYCvpU",
        "playlist": "CHARLY-HOUSE",
        "titre": "Cowboy Bebop - Tank! (Bass Cover) (Play Along Tabs In Video)",
        "start_minute": 1359.9666666666665
    },
    {
        "duree": 210,
        "id": "PHW3GmSPwzU",
        "playlist": "CHARLY-HOUSE",
        "titre": "NIGHT DANCER (BIG Naughty Remix)",
        "start_minute": 1364.033333333333
    },
    {
        "duree": 252,
        "id": "m5MM_QSiYM8",
        "playlist": "CHARLY-HOUSE",
        "titre": "Ariane",
        "start_minute": 1367.533333333333
    },
    {
        "duree": 242,
        "id": "N0TA8xXWSqE",
        "playlist": "CHARLY-HOUSE",
        "titre": "Smooth Operator - TikTok Remix",
        "start_minute": 1371.7333333333331
    },
    {
        "duree": 206,
        "id": "B_1moEBS4TE",
        "playlist": "CHARLY-LOVE",
        "titre": "Hate It Or Love It",
        "start_minute": 1375.7666666666664
    },
    {
        "duree": 326,
        "id": "eK5ozrSgqeI",
        "titre": "Passing Breeze from \"Outrun\" - Big Band Jazz version (The 8-Bit Big Band)",
        "playlist": "CHARLY-RADIO (77 titres)",
        "start_minute": 1380.0
    },
    {
        "duree": 266,
        "id": "friqL2l8rNE",
        "playlist": "CHARLY-CHILL",
        "titre": "GOLD",
        "start_minute": 1385.4333333333334
    },
    {
        "duree": 231,
        "id": "URR_Nv-6MZs",
        "playlist": "CHARLY-CHILL",
        "titre": "喜劇",
        "start_minute": 1389.8666666666668
    },
    {
        "duree": 295,
        "id": "ljEzt2I7IFo",
        "playlist": "CHARLY-CHILL",
        "titre": "King Minos",
        "start_minute": 1393.7166666666667
    },
    {
        "duree": 196,
        "id": "wj9OTLIautc",
        "playlist": "CHARLY-CHILL",
        "titre": "Hate Dancin'",
        "start_minute": 1398.6333333333334
    },
    {
        "duree": 213,
        "id": "wgqUhK32n1c",
        "playlist": "CHARLY-CHILL",
        "titre": "The Door",
        "start_minute": 1401.9
    },
    {
        "duree": 145,
        "id": "gkmgUjDQJ2c",
        "playlist": "CHARLY-CHILL",
        "titre": "Forget",
        "start_minute": 1405.45
    },
    {
        "duree": 258,
        "id": "lt2cHiJABOI",
        "playlist": "CHARLY-CHILL",
        "titre": "Messy (Sped Up)",
        "start_minute": 1407.8666666666668
    },
    {
        "duree": 328,
        "id": "WRLwTO_T52U",
        "playlist": "CHARLY-CHILL",
        "titre": "Inner City Blues (Make Me Wanna Holler)",
        "start_minute": 1412.1666666666667
    },
    {
        "duree": 161,
        "id": "gkTQQFGABl8",
        "playlist": "CHARLY-CHILL",
        "titre": "On My Way",
        "start_minute": 1417.6333333333334
    },
    {
        "duree": 274,
        "id": "cl_AtaYJZpk",
        "playlist": "CHARLY-CHILL",
        "titre": "Moving Forward",
        "start_minute": 1420.3166666666668
    },
    {
        "duree": 249,
        "id": "BxqYUbNR-c0",
        "playlist": "CHARLY-CHILL",
        "titre": "サカナクション / 忘れられないの　-Music Video-",
        "start_minute": 1424.8833333333334
    },
    {
        "duree": 265,
        "id": "Cu19WlR_UvA",
        "playlist": "CHARLY-CHILL",
        "titre": "Shoody - Tokyo Melody",
        "start_minute": 1429.0333333333335
    },
    {
        "duree": 249,
        "id": "9RHFFeQ2tu4",
        "titre": "Fever The Ghost - SOURCE (official music video)",
        "playlist": "CHARLY-RADIO (77 titres)",
        "start_minute": 1433.4500000000003
    },
    {
        "duree": 262,
        "id": "krJ7k1gG_28",
        "playlist": "Charly-RapPop",
        "titre": "Bigflo & Oli - INSOLENT #5",
        "start_minute": 1437.6000000000004
    }
]